batch.py
batchable-0.2.2.dist-info/WHEEL
batchable-0.2.2.dist-info/METADATA
batchable-0.2.2.dist-info/RECORD
