Metadata-Version: 2.1
Name: batchable
Version: 0.2.2
Summary: Hide your batch logic away from the actual code.
Home-page: https://github.com/L3viathan/batchable
Author: L3viathan
Author-email: git@l3vi.de
Requires-Python: >=3.7,<4.0
Classifier: Programming Language :: Python :: 3
Classifier: Programming Language :: Python :: 3.10
Classifier: Programming Language :: Python :: 3.7
Classifier: Programming Language :: Python :: 3.8
Classifier: Programming Language :: Python :: 3.9
Project-URL: Repository, https://github.com/L3viathan/batchable
